[
  {
    "full_name": "WordPress/Documentation-Issue-Tracker",
    "stargazers_count": 15,
    "open_issues_count": 69,
    "forks_count": 4
  },
  {
    "full_name": "Automattic/_s",
    "stargazers_count": 10483,
    "open_issues_count": 55,
    "forks_count": 3124
  },
  {
    "full_name": "jeffreyvr/tailpress",
    "stargazers_count": 491,
    "open_issues_count": 1,
    "forks_count": 78
  },
  {
    "full_name": "WordPress/pattern-directory",
    "stargazers_count": 68,
    "open_issues_count": 42,
    "forks_count": 18
  },
  {
    "full_name": "kr1sp1n/awesome-gemini",
    "stargazers_count": 555,
    "open_issues_count": 5,
    "forks_count": 68
  },
  {
    "full_name": "module-federation/microlib-examples",
    "stargazers_count": 22,
    "open_issues_count": 1,
    "forks_count": 5
  },
  {
    "full_name": "ryersondmp/sa11y",
    "stargazers_count": 113,
    "open_issues_count": 5,
    "forks_count": 15
  },
  {
    "full_name": "sdras/js-explorer",
    "stargazers_count": 240,
    "open_issues_count": 4,
    "forks_count": 10
  },
  {
    "full_name": "trekhleb/learn-python",
    "stargazers_count": 11779,
    "open_issues_count": 4,
    "forks_count": 1874
  },
  {
    "full_name": "WordPress/theme-experiments",
    "stargazers_count": 401,
    "open_issues_count": 53,
    "forks_count": 145
  },
  {
    "full_name": "geekcomputers/Python",
    "stargazers_count": 24580,
    "open_issues_count": 225,
    "forks_count": 10648
  },
  {
    "full_name": "WordPress/wordpress-develop",
    "stargazers_count": 1184,
    "open_issues_count": 575,
    "forks_count": 1056
  },
  {
    "full_name": "WordPress/WordPress",
    "stargazers_count": 15886,
    "open_issues_count": 2,
    "forks_count": 10819
  },
  {
    "full_name": "joshbuchea/HEAD",
    "stargazers_count": 28980,
    "open_issues_count": 19,
    "forks_count": 1964
  },
  {
    "full_name": "Automattic/themes",
    "stargazers_count": 443,
    "open_issues_count": 1317,
    "forks_count": 231
  },
  {
    "full_name": "concrete-utopia/utopia",
    "stargazers_count": 3324,
    "open_issues_count": 184,
    "forks_count": 115
  },
  {
    "full_name": "snowpackjs/astro",
    "stargazers_count": 10118,
    "open_issues_count": 119,
    "forks_count": 488
  },
  {
    "full_name": "arabold/serverless-react-boilerplate",
    "stargazers_count": 129,
    "open_issues_count": 1,
    "forks_count": 48
  },
  {
    "full_name": "cassidoo/pokemon-feature-flags",
    "stargazers_count": 15,
    "open_issues_count": 0,
    "forks_count": 2
  },
  {
    "full_name": "sdras/career-ladders",
    "stargazers_count": 605,
    "open_issues_count": 2,
    "forks_count": 42
  },
  {
    "full_name": "takayukister/contact-form-7",
    "stargazers_count": 149,
    "open_issues_count": 7,
    "forks_count": 78
  },
  {
    "full_name": "WordPress/gutenberg",
    "stargazers_count": 7478,
    "open_issues_count": 4474,
    "forks_count": 2730
  },
  {
    "full_name": "EbookFoundation/free-programming-books",
    "stargazers_count": 220075,
    "open_issues_count": 35,
    "forks_count": 47031
  },
  {
    "full_name": "prismicio/gatsby-blog",
    "stargazers_count": 35,
    "open_issues_count": 2,
    "forks_count": 21
  },
  {
    "full_name": "freeCodeCamp/how-to-contribute-to-open-source",
    "stargazers_count": 6068,
    "open_issues_count": 68,
    "forks_count": 1330
  },
  {
    "full_name": "KnisterPeter/vscode-commitizen",
    "stargazers_count": 196,
    "open_issues_count": 4,
    "forks_count": 34
  },
  {
    "full_name": "codebushi/gatsby-starter-dimension",
    "stargazers_count": 316,
    "open_issues_count": 33,
    "forks_count": 201
  },
  {
    "full_name": "sveltejs/kit",
    "stargazers_count": 6741,
    "open_issues_count": 360,
    "forks_count": 553
  },
  {
    "full_name": "tc39/proposals",
    "stargazers_count": 14678,
    "open_issues_count": 6,
    "forks_count": 639
  },
  {
    "full_name": "tc39/ecma262",
    "stargazers_count": 12900,
    "open_issues_count": 359,
    "forks_count": 1168
  }
]